RSensePy/__init__.py
RSensePy/clip_withBB_function.py
RSensePy/clip_withSHP_function.py
RSensePy/cloudMask_clip.py
RSensePy/indexcal.py
RSensePy/writeRasterFunction.py
RSensePy-0.0.4.dist-info/METADATA
RSensePy-0.0.4.dist-info/WHEEL
RSensePy-0.0.4.dist-info/top_level.txt
RSensePy-0.0.4.dist-info/RECORD
