Metadata-Version: 2.1
Name: RSensePy
Version: 0.0.4
Summary: Biophysical parameter calculator for Sentinel 2 and Landsat 8,9 data
Home-page: https://github.com/richiedlon/SoftwareDevProject
Author: richiedlon/opeyami
License: MIT
Requires-Python: >=3.9.16
Requires-Dist: rasterio (>=1.3.0)
Requires-Dist: matplotlib (>=3.7.0)
Requires-Dist: shapely (>=2.0.0)
Requires-Dist: Fiona (>=1.9.4.post1)
Requires-Dist: geopandas (>=0.13.0)
